modules/__init__.py
modules/betterDateTime.py
modules/betterLogging.py
modules/voice.py
zmp-6.9.dist-info/LICENSE
zmp-6.9.dist-info/METADATA
zmp-6.9.dist-info/WHEEL
zmp-6.9.dist-info/top_level.txt
zmp-6.9.dist-info/RECORD
