Metadata-Version: 2.1
Name: zmp
Version: 6.9
Summary: A few helpful python modules
Home-page: https://github.com/ZoeWithTheE/zm
Author: Zoe
Author-email: zoe@zmp.lol
Classifier: Programming Language :: Python :: 3
Classifier: License :: OSI Approved :: MIT License
Classifier: Operating System :: OS Independent
License-File: LICENSE
